microcosm/__init__.py
microcosm/api.py
microcosm/caching.py
microcosm/constants.py
microcosm/decorators.py
microcosm/errors.py
microcosm/example.py
microcosm/hooks.py
microcosm/metadata.py
microcosm/object_graph.py
microcosm/opaque.py
microcosm/profile.py
microcosm/py.typed
microcosm/registry.py
microcosm/typing.py
microcosm/config/__init__.py
microcosm/config/api.py
microcosm/config/model.py
microcosm/config/sentinel.py
microcosm/config/types.py
microcosm/config/validation.py
microcosm/loaders/__init__.py
microcosm/loaders/compose.py
microcosm/loaders/environment.py
microcosm/loaders/keys.py
microcosm/loaders/settings.py
microcosm/scoping/__init__.py
microcosm/scoping/decorators.py
microcosm/scoping/factories.py
microcosm/scoping/object_graph.py
microcosm/scoping/proxies.py
microcosm-4.1.0.dist-info/LICENSE
microcosm-4.1.0.dist-info/METADATA
microcosm-4.1.0.dist-info/WHEEL
microcosm-4.1.0.dist-info/entry_points.txt
microcosm-4.1.0.dist-info/top_level.txt
microcosm-4.1.0.dist-info/RECORD
