Metadata-Version: 2.1
Name: microcosm
Version: 4.1.0
Summary: Microcosm - Simple microservice configuration
Home-page: https://github.com/globality-corp/microcosm
Author: Globality Engineering
Author-email: engineering@globality.com
Keywords: microcosm
Requires-Python: >=3.9
License-File: LICENSE
Requires-Dist: importlib-metadata >=3.6
Requires-Dist: inflection >=0.5.1
Requires-Dist: lazy >=1.6
Provides-Extra: build
Requires-Dist: coverage >=7.3.2 ; extra == 'build'
Requires-Dist: flake8-isort >=6.1.1 ; extra == 'build'
Requires-Dist: flake8-logging-format >=1.0.0 ; extra == 'build'
Requires-Dist: flake8-print >=5.0.0 ; extra == 'build'
Requires-Dist: flake8 >=6.1.0 ; extra == 'build'
Requires-Dist: mypy >=1.7.0 ; extra == 'build'
Requires-Dist: PyHamcrest >=2.1.0 ; extra == 'build'
Requires-Dist: pytest-cov >=4.1.0 ; extra == 'build'
Requires-Dist: pytest >=7.4.3 ; extra == 'build'
